Spec7plot/__init__.py
Spec7plot/cube.py
Spec7plot/plot.py
Spec7plot/register.py
Spec7plot/src/__init__.py
Spec7plot/src/cube.py
Spec7plot/src/plot.py
Spec7plot/src/register.py
Spec7plot-1.2.6.dist-info/METADATA
Spec7plot-1.2.6.dist-info/WHEEL
Spec7plot-1.2.6.dist-info/top_level.txt
Spec7plot-1.2.6.dist-info/RECORD
