Metadata-Version: 2.1
Name: Spec7plot
Version: 1.2.6
Summary: Spectral figure plotting package for 7-Dimensional Telescope users by Won-Hyeong Lee
Home-page: https://github.com/Yicircle/Spec7plot
Author: Won-Hyeong Lee
Author-email: wohy1220@gmail.com
Classifier: Programming Language :: Python :: 3.10
Classifier: Programming Language :: Python :: 3.11
Classifier: Programming Language :: Python :: 3.12
Requires-Python: >=3.10
Requires-Dist: numpy
Requires-Dist: astropy
Requires-Dist: matplotlib
Requires-Dist: seaborn
Requires-Dist: pathlib
Requires-Dist: photutils
Requires-Dist: reproject
